{
 "updated": "2026-06-10 21:06 UTC",
 "items": [
  {
   "time": "2026-06-10 12:30 ET",
   "title": "午盘急转直下：纳指 -1.27%（25352），标普 -1.0%——伊朗战事升级 + 霍尔木兹海峡近乎关闭推高油价",
   "impact": "negative",
   "note": "地缘风险叠加 CPI 4.2%（三年新高）双重施压。AI/芯片领跌：SMCI 宣布70亿美元增发暴跌17%，英伟达、美光续跌。注意：模型的事件研究显示地缘冲击30日后通常修复（LR≈1.0），恐慌抛售历史上不是好选择。",
   "source": "TheStreet/Fool/247WallSt",
   "kind": "curated"
  },
  {
   "time": "2026-06-10 08:30 ET",
   "title": "5月CPI：总体 4.2% YoY（环比+0.5%，能源+3.9%主推），核心 2.9%（环比+0.2%低于预期）",
   "impact": "neutral",
   "note": "市场初反应温和（期货-0.5%），午盘下跌主因是中东而非CPI本身。利率期货：美联储年内按兵不动，12月或加息。下一个关键节点：6/16-17 FOMC（含SEP）。",
   "source": "CNBC/BLS",
   "kind": "curated"
  },
  {
   "time": "2026-06-10 21:00 UTC",
   "title": "Oracle beats on earnings, but stock drops on plans to raise another $20 billion",
   "impact": "neutral",
   "note": "",
   "source": "CNBC Top News",
   "kind": "auto"
  },
  {
   "time": "2026-06-10 20:58 UTC",
   "title": "Why Nike saw its stock downgraded a day before the World Cup’s kickoff",
   "impact": "neutral",
   "note": "",
   "source": "MarketWatch",
   "kind": "auto"
  },
  {
   "time": "2026-06-10 20:49 UTC",
   "title": "Oracle’s stock slides after earnings, as the steep price of AI spooks investors",
   "impact": "neutral",
   "note": "",
   "source": "MarketWatch",
   "kind": "auto"
  },
  {
   "time": "2026-06-10 20:16 UTC",
   "title": "Worried that big IPOs will torpedo the stock market? These factors suggest otherwise.",
   "impact": "neutral",
   "note": "",
   "source": "MarketWatch",
   "kind": "auto"
  },
  {
   "time": "2026-06-10 20:01 UTC",
   "title": "Amazon trucking expansion sparks freight stock sell-off",
   "impact": "negative",
   "note": "",
   "source": "CNBC Top News",
   "kind": "auto"
  }
 ]
}