{"generated":"2026-07-20T21:36:34Z","quotes":{"SPCX":{"price":119.85,"prev_close":123.99,"chg_pct":-3.34,"ts":1784577600,"vol":56256348,"bid":120.28,"ask":120.32},"NASDAQ":{"price":25508.07,"prev_close":25520.24,"chg_pct":-0.05,"ts":1784582159,"vol":6047704000},"SP500":{"price":7443.28,"prev_close":7457.69,"chg_pct":-0.19,"ts":1784581698,"vol":2726531000},"BTC":{"price":65394.07,"prev_close":64680.23,"chg_pct":1.1,"ts":1784583390,"vol":31560366080}},"crypto":{"BTC":65378.0,"ETH":1904.51,"XLM":0.189186,"DOGE":0.072247,"HOME":0.007104,"SOL":77.89,"BNB":571.38},"aud_rate":0.7,"fear_greed":[{"value":"29","value_classification":"Fear","timestamp":"1784505600","time_until_update":"8605"},{"value":"28","value_classification":"Fear","timestamp":"1784419200"},{"value":"25","value_classification":"Extreme Fear","timestamp":"1784332800"},{"value":"27","value_classification":"Fear","timestamp":"1784246400"},{"value":"25","value_classification":"Extreme Fear","timestamp":"1784160000"},{"value":"25","value_classification":"Extreme Fear","timestamp":"1784073600"},{"value":"22","value_classification":"Extreme Fear","timestamp":"1783987200"}]}