{
  "generated": "2026-07-14T14:46:31Z",
  "date_range": [
    "2014-10-15",
    "2026-07-14"
  ],
  "n_days": 2952,
  "signal": "BTC 20日动量，阈值 ±5%；前向 20 日",
  "conditional": {
    "base": {
      "n": 2932,
      "mean_pct": 1.35,
      "up_rate": 66.5,
      "p10": -5.34,
      "p90": 7.06,
      "worst": -29.05,
      "pct_neg": 33.5
    },
    "pos": {
      "n": 1302,
      "mean_pct": 1.78,
      "up_rate": 72.7,
      "p10": -4.43,
      "p90": 7.11,
      "worst": -29.05,
      "pct_neg": 27.3
    },
    "neutral": {
      "n": 725,
      "mean_pct": 1.33,
      "up_rate": 64.1,
      "p10": -5.25,
      "p90": 7.08,
      "worst": -18.38,
      "pct_neg": 35.9
    },
    "neg": {
      "n": 905,
      "mean_pct": 0.75,
      "up_rate": 59.4,
      "p10": -6.86,
      "p90": 6.86,
      "worst": -17.78,
      "pct_neg": 40.6
    }
  },
  "cond_pos_minus_neg_uprate_pp": 13.3,
  "control_nasdaq_own_mom": {
    "pos_minus_neg_uprate_pp": 9.4,
    "btc_incremental_pp": 3.9
  },
  "backtest": {
    "rule": "BTC动量<-5%→空仓，否则满仓纳指；次日生效；单边成本 5bps",
    "cost_bps": 5.0,
    "n_switches": 214,
    "time_in_market_pct": 68.9,
    "strategy": {
      "total_return_pct": 358.5,
      "cagr_pct": 13.84,
      "sharpe": 0.94,
      "max_dd_pct": -29.5
    },
    "buyhold": {
      "total_return_pct": 516.4,
      "cagr_pct": 16.75,
      "sharpe": 0.83,
      "max_dd_pct": -36.4
    },
    "excess_cagr_pp": -2.91,
    "dd_shallower_pp": 6.9,
    "sharpe_diff": 0.11
  },
  "regimes": [
    {
      "period": "2014-2017",
      "n": 809,
      "cond_pos_minus_neg_uprate_pp": 3.6,
      "strat_cagr_pct": 13.53,
      "buyhold_cagr_pct": 16.53,
      "edge_holds": true
    },
    {
      "period": "2018-2020",
      "n": 756,
      "cond_pos_minus_neg_uprate_pp": 8.7,
      "strat_cagr_pct": 20.77,
      "buyhold_cagr_pct": 23.17,
      "edge_holds": true
    },
    {
      "period": "2021-2023",
      "n": 753,
      "cond_pos_minus_neg_uprate_pp": 15.7,
      "strat_cagr_pct": 2.66,
      "buyhold_cagr_pct": 5.25,
      "edge_holds": true
    },
    {
      "period": "2024-2026",
      "n": 634,
      "cond_pos_minus_neg_uprate_pp": 25.3,
      "strat_cagr_pct": 20.54,
      "buyhold_cagr_pct": 24.36,
      "edge_holds": true
    }
  ],
  "verdict": "信号真·风险取舍：方向同号 4/4 段(其中 3 段优势≥5pp；早段约3pp接近噪声、强度随期递增)；裸 overlay 让出 2.91pp 年化，换 Sharpe 0.94 vs 0.83、回撤 -29.5% vs -36.4%(浅 6.9pp)——但属单一历史路径、无置信区间，可能不重复。要风险调整收益的可参考，要最大绝对收益的死拿更好。已对照纳指自身20日动量(同口径差 9.4pp)：BTC 多给约 3.9pp 增量、不只是大盘动量代理",
  "caveat": "出格区·把红线此前剥掉的方向亮出来诚实检验。非荐股、非保证、会错、过去≠未来；BTC 与纳指同属高风险资产，相关≠因果；已对照纳指自身20日动量(同口径差 9.4pp)：BTC 多给约 3.9pp 增量、不只是大盘动量代理；Sharpe/回撤改善属单一历史路径、无置信区间；FRAGILE(符号一致性0.8)→ 看体制段。每跑 append 计分。"
}