{"generated":"2026-07-22T19:38:36Z","quotes":{"SPCX":{"price":116.14,"prev_close":123.54,"chg_pct":-5.99,"ts":1784749116,"vol":72332440,"bid":116.15,"ask":116.16},"NASDAQ":{"price":25709.89,"prev_close":25837.21,"chg_pct":-0.49,"ts":1784749114,"vol":5268622000},"SP500":{"price":7498.73,"prev_close":7509.2,"chg_pct":-0.14,"ts":1784749116,"vol":2030995000},"BTC":{"price":65878.42,"prev_close":66508.87,"chg_pct":-0.95,"ts":1784749114,"vol":28921237504}},"crypto":{"BTC":65884.0,"ETH":1926.96,"XLM":0.18763,"DOGE":0.072485,"HOME":0.006291,"SOL":77.63,"BNB":569.54},"aud_rate":0.6994,"fear_greed":[{"value":"33","value_classification":"Fear","timestamp":"1784678400","time_until_update":"15683"},{"value":"25","value_classification":"Extreme Fear","timestamp":"1784592000"},{"value":"29","value_classification":"Fear","timestamp":"1784505600"},{"value":"28","value_classification":"Fear","timestamp":"1784419200"},{"value":"25","value_classification":"Extreme Fear","timestamp":"1784332800"},{"value":"27","value_classification":"Fear","timestamp":"1784246400"},{"value":"25","value_classification":"Extreme Fear","timestamp":"1784160000"}]}