{"generated":"2026-07-05T21:47:39Z","quotes":{"SPCX":{"price":162.0,"prev_close":157.54,"chg_pct":2.83,"ts":1783022400,"vol":61257120},"NASDAQ":{"price":25832.67,"prev_close":26040.0,"chg_pct":-0.8,"ts":1783026959,"vol":8519282000},"SP500":{"price":7483.24,"prev_close":7483.23,"chg_pct":0.0,"ts":1783024935,"vol":3414978000},"BTC":{"price":62936.03,"prev_close":63087.74,"chg_pct":-0.24,"ts":1783288053,"vol":15672137728}},"crypto":{"BTC":62936.0,"ETH":1780.64,"XLM":0.201895,"DOGE":0.077442,"HOME":0.016387,"SOL":81.51,"BNB":588.25},"aud_rate":0.6941,"fear_greed":[{"value":"23","value_classification":"Extreme Fear","timestamp":"1783209600","time_until_update":"7941"},{"value":"22","value_classification":"Extreme Fear","timestamp":"1783123200"},{"value":"21","value_classification":"Extreme Fear","timestamp":"1783036800"},{"value":"19","value_classification":"Extreme Fear","timestamp":"1782950400"},{"value":"11","value_classification":"Extreme Fear","timestamp":"1782864000"},{"value":"15","value_classification":"Extreme Fear","timestamp":"1782777600"},{"value":"12","value_classification":"Extreme Fear","timestamp":"1782691200"}]}