{"generated":"2026-07-10T17:25:45Z","quotes":{"SPCX":{"price":148.76,"prev_close":152.16,"chg_pct":-2.23,"ts":1783704343,"vol":25809362,"bid":148.75,"ask":148.76},"NASDAQ":{"price":26265.16,"prev_close":26206.89,"chg_pct":0.22,"ts":1783704343,"vol":3882068000},"SP500":{"price":7565.68,"prev_close":7543.64,"chg_pct":0.29,"ts":1783704345,"vol":1122596000},"BTC":{"price":63936.0,"prev_close":63184.8,"chg_pct":1.19,"ts":1783704343,"vol":26637426688}},"crypto":{"BTC":63917.0,"ETH":1791.72,"XLM":0.18959,"DOGE":0.073958,"HOME":0.015654,"SOL":77.73,"BNB":576.25},"aud_rate":0.6957,"fear_greed":[{"value":"23","value_classification":"Extreme Fear","timestamp":"1783641600","time_until_update":"23655"},{"value":"22","value_classification":"Extreme Fear","timestamp":"1783555200"},{"value":"20","value_classification":"Extreme Fear","timestamp":"1783468800"},{"value":"27","value_classification":"Fear","timestamp":"1783382400"},{"value":"24","value_classification":"Extreme Fear","timestamp":"1783296000"},{"value":"23","value_classification":"Extreme Fear","timestamp":"1783209600"},{"value":"22","value_classification":"Extreme Fear","timestamp":"1783123200"}]}